logadu/__init__.py
logadu/cli/__init__.py
logadu/cli/main.py
logadu/commands/__init__.py
logadu/commands/convert.py
logadu/commands/evaluate.py
logadu/commands/merge.py
logadu/commands/parse.py
logadu/commands/predict.py
logadu/commands/represent.py
logadu/commands/run.py
logadu/commands/seq.py
logadu/commands/train.py
logadu/commands/vectorize.py
logadu/commands/vectorize_bert.py
logadu/data/__init__.py
logadu/data/dataloader.py
logadu/data/trainer.py
logadu/datamodules/__init__.py
logadu/datamodules/agg_vector_template.py
logadu/datamodules/deeplog.py
logadu/datamodules/index.py
logadu/datamodules/loganomaly.py
logadu/datamodules/logbert.py
logadu/datamodules/vector_template.py
logadu/feat-repr/__init__.py
logadu/feat-repr/one_hot_encoder.py
logadu/logic/__init__.py
logadu/logic/autoencoder_lightning.py
logadu/logic/conversion_logic.py
logadu/logic/deeplog_datamodule.py
logadu/logic/deeplog_lightning.py
logadu/logic/logbert_datamodule.py
logadu/logic/logbert_lightning.py
logadu/logic/logrobust_datamodule.py
logadu/logic/logrobust_lightning.py
logadu/logic/neurallog_lightning.py
logadu/logic/representation_logic.py
logadu/logic/traditional_logic.py
logadu/logic/vectorization_bert.py
logadu/logic/vectorization_logic.py
logadu/ml/__init__.py
logadu/ml/knn.py
logadu/modellightning/__init__.py
logadu/modellightning/agg_vector_template.py
logadu/modellightning/autoencoder.py
logadu/modellightning/deeplog.py
logadu/modellightning/loganomaly.py
logadu/modellightning/logbert.py
logadu/modellightning/logcnn.py
logadu/modellightning/logrobust.py
logadu/modellightning/neurallog.py
logadu/modellightning/plelog.py
logadu/models/__init__.py
logadu/models/autoencoder.py
logadu/models/deeplog.py
logadu/models/knn.py
logadu/models/loganomaly.py
logadu/models/logbert.py
logadu/models/logcnn.py
logadu/models/logrobust.py
logadu/models/neurallog.py
logadu/models/plelog.py
logadu/parsers/__init__.py
logadu/parsers/drain.py
logadu/parsers/ft_tree.py
logadu/parsers/merging.py
logadu-0.2.12.dist-info/METADATA
logadu-0.2.12.dist-info/WHEEL
logadu-0.2.12.dist-info/entry_points.txt
logadu-0.2.12.dist-info/top_level.txt
logadu-0.2.12.dist-info/RECORD
